gmailbox/__init__.py
gmailbox/gmailbox.py
tests/__init__.py
tests/test_gmailbox.py
gmailimbox-0.1.0.dist-info/METADATA
gmailimbox-0.1.0.dist-info/WHEEL
gmailimbox-0.1.0.dist-info/top_level.txt
gmailimbox-0.1.0.dist-info/RECORD
