Metadata-Version: 2.1
Name: gmailimbox
Version: 0.1.0
Summary: A simple Gmail API client to fetch emails based on specific criteria
Home-page: https://github.com/santoshray02/gmailimbox
Author: Santosh Kumar
Author-email: rayskumar02@gmail.com
Classifier: Development Status :: 3 - Alpha
Classifier: Intended Audience :: Developers
Classifier: Natural Language :: English
Classifier: License :: OSI Approved :: MIT License
Classifier: Programming Language :: Python :: 3
Classifier: Programming Language :: Python :: 3.7
Classifier: Programming Language :: Python :: 3.8
Classifier: Programming Language :: Python :: 3.9
Classifier: Programming Language :: Python :: 3.10
Requires-Python: >=3.7
Requires-Dist: google-api-python-client
Requires-Dist: google-auth-httplib2
Requires-Dist: google-auth-oauthlib
